{
  "$schema": "https://developer.microsoft.com/json-schemas/fabric/item/report/definition/visualContainer/2.4.0/schema.json",
  "name": "68b06577017b5656aab1",
  "position": {
    "x": 743.8012984692358,
    "y": 161.93460003573767,
    "z": 5000,
    "height": 222.31699326940259,
    "width": 256.62517124307584
  },
  "visual": {
    "visualType": "slicer",
    "query": {
      "queryState": {
        "Values": {
          "projections": [
            {
              "field": {
                "Column": {
                  "Expression": {
                    "SourceRef": {
                      "Entity": "V_Dim_FB_RptBranchHier"
                    }
                  },
                  "Property": "RegionName"
                }
              },
              "queryRef": "V_Dim_FB_RptBranchHier.RegionName",
              "nativeQueryRef": "RegionName",
              "active": true
            }
          ]
        }
      }
    },
    "objects": {
      "data": [
        {
          "properties": {
            "mode": {
              "expr": {
                "Literal": {
                  "Value": "'Basic'"
                }
              }
            }
          }
        }
      ],
      "general": [
        {
          "properties": {}
        }
      ]
    },
    "drillFilterOtherVisuals": true
  }
}