{
  "$schema": "https://developer.microsoft.com/json-schemas/fabric/item/report/definition/visualContainer/2.4.0/schema.json",
  "name": "62d77a8510963d801605",
  "position": {
    "x": 19.363295880149856,
    "y": 6.3905325443787078,
    "z": 2000,
    "height": 46.153846153846153,
    "width": 310.63670411985015,
    "tabOrder": 16
  },
  "visual": {
    "visualType": "textbox",
    "objects": {
      "general": [
        {
          "properties": {
            "paragraphs": [
              {
                "textRuns": [
                  {
                    "value": "Total % Sold",
                    "textStyle": {
                      "fontSize": "16pt"
                    }
                  }
                ]
              }
            ]
          }
        }
      ]
    },
    "visualContainerObjects": {
      "background": [
        {
          "properties": {
            "transparency": {
              "expr": {
                "Literal": {
                  "Value": "100D"
                }
              }
            }
          }
        }
      ],
      "title": [
        {
          "properties": {
            "text": {
              "expr": {
                "Literal": {
                  "Value": "'Name box 1'"
                }
              }
            }
          }
        }
      ]
    },
    "drillFilterOtherVisuals": true
  },
  "parentGroupName": "669b8add1e70e8051720"
}