{
  "$schema": "https://developer.microsoft.com/json-schemas/fabric/item/report/definition/page/2.0.0/schema.json",
  "name": "b863b307c6851346b3b1",
  "displayName": "Bottom Performer",
  "displayOption": "FitToPage",
  "height": 900,
  "width": 1350,
  "visibility": "HiddenInViewMode",
  "visualInteractions": [
    {
      "source": "e1473bb8d60ea31b70e4",
      "target": "cfa4263ed474a39777ac",
      "type": "NoFilter"
    },
    {
      "source": "e1473bb8d60ea31b70e4",
      "target": "19c14ace1c20cb786816",
      "type": "NoFilter"
    },
    {
      "source": "e1473bb8d60ea31b70e4",
      "target": "0e6c2a1a47e24aacc204",
      "type": "NoFilter"
    },
    {
      "source": "e1473bb8d60ea31b70e4",
      "target": "b04f03ce0d6402560230",
      "type": "NoFilter"
    },
    {
      "source": "e1473bb8d60ea31b70e4",
      "target": "ae52d340edc355e8e19a",
      "type": "NoFilter"
    },
    {
      "source": "e1473bb8d60ea31b70e4",
      "target": "bee8de397472ef5e616c",
      "type": "NoFilter"
    }
  ]
}