{
  "$schema": "https://developer.microsoft.com/json-schemas/fabric/item/report/definition/visualContainer/2.4.0/schema.json",
  "name": "c681f513dbea30345a05",
  "position": {
    "x": 641,
    "y": 58,
    "z": 10000,
    "height": 31,
    "width": 76,
    "tabOrder": 10000
  },
  "visual": {
    "visualType": "textbox",
    "objects": {
      "general": [
        {
          "properties": {
            "paragraphs": [
              {
                "textRuns": [
                  {
                    "value": "Territory",
                    "textStyle": {
                      "fontFamily": "Segoe (Bold)"
                    }
                  }
                ],
                "horizontalTextAlignment": "right"
              }
            ]
          }
        }
      ]
    },
    "visualContainerObjects": {
      "background": [
        {
          "properties": {
            "color": {
              "solid": {
                "color": {
                  "expr": {
                    "Literal": {
                      "Value": "'#CCCBCA'"
                    }
                  }
                }
              }
            },
            "transparency": {
              "expr": {
                "Literal": {
                  "Value": "100D"
                }
              }
            }
          }
        }
      ]
    },
    "drillFilterOtherVisuals": true
  }
}