{
  "$schema": "https://developer.microsoft.com/json-schemas/fabric/item/report/definition/visualContainer/2.4.0/schema.json",
  "name": "827be6f030f7a456ad28",
  "position": {
    "x": 305,
    "y": 89.666666666666657,
    "z": 8500,
    "height": 56,
    "width": 100,
    "tabOrder": 6000
  },
  "visual": {
    "visualType": "tableEx",
    "query": {
      "queryState": {
        "Values": {
          "projections": [
            {
              "field": {
                "Measure": {
                  "Expression": {
                    "SourceRef": {
                      "Entity": "Measure Table"
                    }
                  },
                  "Property": "Rate_Per_Case_AOP_FCST_YA_Selection_TL"
                }
              },
              "queryRef": "Measure Table.Rate_Per_Case_AOP_FCST_YA_Selection_TL",
              "nativeQueryRef": " ",
              "displayName": " "
            }
          ]
        }
      },
      "sortDefinition": {
        "sort": [
          {
            "field": {
              "Measure": {
                "Expression": {
                  "SourceRef": {
                    "Entity": "Measure Table"
                  }
                },
                "Property": "Rate_Per_Case_AOP_FCST_YA_Selection_TL"
              }
            },
            "direction": "Descending"
          }
        ],
        "isDefaultSort": true
      }
    },
    "objects": {
      "grid": [
        {
          "properties": {
            "outlineColor": {
              "solid": {
                "color": {
                  "expr": {
                    "ThemeDataColor": {
                      "ColorId": 0,
                      "Percent": 0
                    }
                  }
                }
              }
            }
          }
        }
      ],
      "values": [
        {
          "properties": {
            "fontFamily": {
              "expr": {
                "Literal": {
                  "Value": "'''Segoe UI Semibold'', wf_segoe-ui_semibold, helvetica, arial, sans-serif'"
                }
              }
            },
            "fontSize": {
              "expr": {
                "Literal": {
                  "Value": "14D"
                }
              }
            }
          }
        }
      ],
      "columnHeaders": [
        {
          "properties": {
            "fontColor": {
              "solid": {
                "color": {
                  "expr": {
                    "ThemeDataColor": {
                      "ColorId": 0,
                      "Percent": 0
                    }
                  }
                }
              }
            },
            "fontSize": {
              "expr": {
                "Literal": {
                  "Value": "9D"
                }
              }
            }
          }
        }
      ]
    },
    "visualContainerObjects": {
      "title": [
        {
          "properties": {
            "text": {
              "expr": {
                "Literal": {
                  "Value": "'Var1'"
                }
              }
            }
          }
        }
      ],
      "padding": [
        {
          "properties": {
            "left": {
              "expr": {
                "Literal": {
                  "Value": "0D"
                }
              }
            },
            "top": {
              "expr": {
                "Literal": {
                  "Value": "0D"
                }
              }
            },
            "bottom": {
              "expr": {
                "Literal": {
                  "Value": "0D"
                }
              }
            },
            "right": {
              "expr": {
                "Literal": {
                  "Value": "0D"
                }
              }
            }
          }
        }
      ]
    },
    "drillFilterOtherVisuals": true
  },
  "parentGroupName": "9231791c735cd23c8404"
}