{
  "$schema": "https://developer.microsoft.com/json-schemas/fabric/item/report/definition/visualContainer/2.4.0/schema.json",
  "name": "c9a9dd93874e4049d011",
  "position": {
    "x": 364.28571428571433,
    "y": 0,
    "z": 3000,
    "height": 35.714285714285715,
    "width": 95.714285714285722,
    "tabOrder": 54
  },
  "visual": {
    "visualType": "textbox",
    "objects": {
      "general": [
        {
          "properties": {
            "paragraphs": [
              {
                "textRuns": [
                  {
                    "value": "Vs Target",
                    "textStyle": {
                      "fontSize": "11pt"
                    }
                  }
                ],
                "horizontalTextAlignment": "center"
              }
            ]
          }
        }
      ]
    },
    "visualContainerObjects": {
      "border": [
        {
          "properties": {
            "show": {
              "expr": {
                "Literal": {
                  "Value": "false"
                }
              }
            },
            "color": {
              "solid": {
                "color": {
                  "expr": {
                    "ThemeDataColor": {
                      "ColorId": 0,
                      "Percent": -0.5
                    }
                  }
                }
              }
            }
          }
        }
      ],
      "background": [
        {
          "properties": {
            "color": {
              "solid": {
                "color": {
                  "expr": {
                    "Literal": {
                      "Value": "'#F7F3ED'"
                    }
                  }
                }
              }
            },
            "show": {
              "expr": {
                "Literal": {
                  "Value": "false"
                }
              }
            }
          }
        }
      ]
    },
    "drillFilterOtherVisuals": true
  },
  "parentGroupName": "f488f434e18368abb799"
}