{
  "$schema": "https://developer.microsoft.com/json-schemas/fabric/item/report/definition/visualContainer/2.4.0/schema.json",
  "name": "eb5193d5554c1190ae43",
  "position": {
    "x": 920.31610629154522,
    "y": 7.911026701646521,
    "z": 2000,
    "height": 83.065780367288468,
    "width": 67.243726963995428
  },
  "visual": {
    "visualType": "tableEx",
    "query": {
      "queryState": {
        "Values": {
          "projections": [
            {
              "field": {
                "Measure": {
                  "Expression": {
                    "SourceRef": {
                      "Entity": "Measure Table"
                    }
                  },
                  "Property": "PeriodLabel"
                }
              },
              "queryRef": "Measure Table.PeriodLabel",
              "nativeQueryRef": "PeriodLabel"
            }
          ]
        }
      }
    },
    "objects": {
      "columnWidth": [
        {
          "properties": {
            "value": {
              "expr": {
                "Literal": {
                  "Value": "48.35589319341392D"
                }
              }
            }
          },
          "selector": {
            "metadata": "Measure Table.PeriodLabel"
          }
        }
      ]
    },
    "drillFilterOtherVisuals": true
  }
}